bowen_test_2/__init__.py
bowen_test_2/server.py
bowen_test_2-0.1.0.dist-info/METADATA
bowen_test_2-0.1.0.dist-info/WHEEL
bowen_test_2-0.1.0.dist-info/top_level.txt
bowen_test_2-0.1.0.dist-info/RECORD
