Metadata-Version: 2.4
Name: bowen-test-2
Version: 0.1.0
Summary: Add your description here
Home-page: 
Author: bowen
Author-email: 704836663@qq.com
Requires-Python: >=3.6
Requires-Dist: mcp[cli]>=1.7.1
Requires-Dist: setuptools>=80.3.1
Requires-Dist: twine>=6.1.0
Requires-Dist: wheel>=0.45.1
Dynamic: author
Dynamic: author-email
Dynamic: requires-python
